MANIFEST.in
README.rst
requirements.txt
setup.cfg
setup.py
awsretry/__init__.py
gd_awsretry.egg-info/PKG-INFO
gd_awsretry.egg-info/SOURCES.txt
gd_awsretry.egg-info/dependency_links.txt
gd_awsretry.egg-info/requires.txt
gd_awsretry.egg-info/top_level.txt