Metadata-Version: 2.1
Name: gd-awsretry
Version: 1.1.1
Summary: Decorate your AWS Boto3 Calls with AWSRetry.backoff(). This will allows your calls to get around the AWS Eventual Consistency Errors.
Home-page: https://github.com/linuxdynasty/awsretry
Author: Allen Sanabria
Author-email: asanabria@linuxdynasty.org
License: MIT
Keywords: boto3 aws retry awsretry backoff
Platform: UNKNOWN
Classifier: Development Status :: 5 - Production/Stable
Classifier: Intended Audience :: Developers
Classifier: Topic :: Software Development :: Build Tools
Classifier: License :: OSI Approved :: MIT License
Classifier: Programming Language :: Python :: 2
Classifier: Programming Language :: Python :: 2.7
Classifier: Programming Language :: Python :: 3
Classifier: Programming Language :: Python :: 3.6
Provides-Extra: test
Provides-Extra: dev
